nervatura/__init__.py
nervatura/store_pb2.py
nervatura/store_pb2.pyi
nervatura/store_pb2_grpc.py
nervatura-6.0.1.dist-info/licenses/LICENSE
nervatura-6.0.1.dist-info/METADATA
nervatura-6.0.1.dist-info/WHEEL
nervatura-6.0.1.dist-info/top_level.txt
nervatura-6.0.1.dist-info/RECORD
