Metadata-Version: 2.4
Name: nervatura
Version: 6.0.1
Summary: Nervatura Framework Python gRPC packages
Home-page: https://github.com/nervatura/nervatura
Author: Csaba Kappel
Author-email: info@nervatura.com
Project-URL: Bug Tracker, https://github.com/nervatura/nervatura/issues
Classifier: Programming Language :: Python :: 3
Classifier: License :: OSI Approved :: GNU General Public License v3 or later (GPLv3+)
Classifier: Operating System :: OS Independent
Requires-Python: >=3.6
License-File: LICENSE
Dynamic: license-file
